bird/__init__.py
bird/object.py
bird_dev-1.0.0a4.dist-info/METADATA
bird_dev-1.0.0a4.dist-info/WHEEL
bird_dev-1.0.0a4.dist-info/top_level.txt
bird_dev-1.0.0a4.dist-info/RECORD
