Metadata-Version: 2.1
Name: bird-dev
Version: 1.0.0a4
Summary: Bird Dev
Author: XiangQinxi
Author-email: XiangQinxi@outlook.com
Classifier: Programming Language :: Python :: 3
Classifier: License :: OSI Approved :: MIT License
Classifier: Operating System :: OS Independent
Requires-Python: >=3
